[
  {
    "id": "dell-latitude-7440",
    "brand": "Dell",
    "name": "Dell Latitude 7440",
    "segment": "Business",
    "price": 1429,
    "cpu": "Intel Core i7-1365U vPro",
    "gpu": "Intel Iris Xe",
    "ram": "16GB LPDDR5",
    "storage": "512GB NVMe SSD",
    "display": "14\" FHD+ ComfortView",
    "battery": "58Wh • ExpressCharge",
    "weight": "1.4kg",
    "image": "/assets/laptop/dell1.jpg",
    "highlights": ["Wi‑Fi 6E + 5G ready", "Smart Card + IR cam", "Thunderbolt 4 x2"]
  },
  {
    "id": "dell-xps-15",
    "brand": "Dell",
    "name": "Dell XPS 15 Creator",
    "segment": "Creator",
    "price": 1899,
    "cpu": "Intel Core i7-13700H",
    "gpu": "NVIDIA RTX 4060 8GB",
    "ram": "32GB DDR5",
    "storage": "1TB Gen4 NVMe",
    "display": "15.6\" OLED 3.5K",
    "battery": "86Wh • Type-C charge",
    "weight": "1.8kg",
    "image": "/assets/laptop/dell2.jpg",
    "highlights": ["100% DCI-P3", "Studio drivers", "Gorilla Glass 6"]
  },
  {
    "id": "hp-elitebook-1040",
    "brand": "HP",
    "name": "HP EliteBook 1040 G11",
    "segment": "Business",
    "price": 1589,
    "cpu": "Intel Core Ultra 7",
    "gpu": "Intel Arc integrated",
    "ram": "16GB LPDDR5x",
    "storage": "1TB NVMe",
    "display": "14\" WUXGA 400 nits",
    "battery": "54Wh • Fast Charge",
    "weight": "1.2kg",
    "image": "/assets/laptop/hp3.webp",
    "highlights": ["Wolf Security", "5MP privacy cam", "Tile tracking ready"]
  },
  {
    "id": "hp-omen-16",
    "brand": "HP",
    "name": "HP Omen 16 Advantage",
    "segment": "Gaming",
    "price": 1799,
    "cpu": "AMD Ryzen 9 7840HS",
    "gpu": "Radeon RX 7700S 8GB",
    "ram": "32GB DDR5",
    "storage": "1TB Gen4 NVMe",
    "display": "16.1\" QHD 240Hz",
    "battery": "83Wh • USB-C PD",
    "weight": "2.3kg",
    "image": "/assets/laptop/hp4.webp",
    "highlights": ["OMEN Tempest cooling", "Per-key RGB", "Wi‑Fi 6E"]
  },
  {
    "id": "lenovo-thinkpad-x1",
    "brand": "Lenovo",
    "name": "Lenovo ThinkPad X1 Carbon Gen 12",
    "segment": "Ultraportable",
    "price": 1699,
    "cpu": "Intel Core Ultra 7",
    "gpu": "Intel Arc integrated",
    "ram": "32GB LPDDR5x",
    "storage": "1TB NVMe",
    "display": "14\" 2.8K OLED",
    "battery": "57Wh • RapidCharge",
    "weight": "1.1kg",
    "image": "/assets/laptop/Lenovo2.webp",
    "highlights": ["MIL‑STD 810H", "Dolby Vision + Atmos", "5G sub‑6 ready"]
  },
  {
    "id": "lenovo-loq-15",
    "brand": "Lenovo",
    "name": "Lenovo LOQ 15",
    "segment": "Gaming",
    "price": 1399,
    "cpu": "Intel Core i7-13650HX",
    "gpu": "NVIDIA RTX 4060 8GB",
    "ram": "16GB DDR5",
    "storage": "1TB NVMe",
    "display": "15.6\" FHD 165Hz",
    "battery": "80Wh • Super Rapid",
    "weight": "2.4kg",
    "image": "/assets/laptop/Lenovo1.webp",
    "highlights": ["ColdFront 5.0", "MUX switch", "Legion TrueStrike keys"]
  }
]
